MANIFEST.in
pyproject.toml
setup.py
fussy/__init__.py
fussy/_shims.py
fussy/asyncinotify.py
fussy/cronlock.py
fussy/errors.py
fussy/filewatch.py
fussy/firmwareconfig.py
fussy/fstransaction.py
fussy/inotify.py
fussy/inotifyasync.py
fussy/install.py
fussy/jsonformat.py
fussy/jsonlog.py
fussy/jsonlogserver.py
fussy/linktree.py
fussy/nbio.py
fussy/pack.py
fussy/processcontrol.py
fussy/southrollback.py
fussy/sseclient.py
fussy/sseserver.py
fussy/tailprotocol.py
fussy/tsname.py
fussy/twrite.py
fussy/unattendedset.py
fussy/unpack.py
fussy/version.py
fussy.egg-info/PKG-INFO
fussy.egg-info/SOURCES.txt
fussy.egg-info/dependency_links.txt
fussy.egg-info/entry_points.txt
fussy.egg-info/requires.txt
fussy.egg-info/top_level.txt
fussy/ssedemo/eventsource.min.js
fussy/ssedemo/eventsource.min.js-LICENSE
fussy/ssedemo/logwatcher.html
fussy/ssedemo/sseclient.html