Metadata-Version: 1.1
Name: fussy
Version: 1.0.32
Summary: Field-Upgradable Software Support
Home-page: http://www.vrplumber.com
Author: Mike C. Fletcher
Author-email: mcfletch@vrplumber.com
License: LGPL
Keywords: firmware,field,upgrade,embedding
Platform: UNKNOWN
Classifier: Programming Language :: Python
Classifier: Operating System :: POSIX :: Linux
Classifier: License :: OSI Approved :: GNU Lesser General Public License v2 (LGPLv2)
